slack_blockkit_builder/__init__.py
slack_blockkit_builder/builder.py
slack_blockkit_builder-0.1.0.dist-info/METADATA
slack_blockkit_builder-0.1.0.dist-info/WHEEL
slack_blockkit_builder-0.1.0.dist-info/top_level.txt
slack_blockkit_builder-0.1.0.dist-info/RECORD
