Metadata-Version: 2.4
Name: slack_blockkit_builder
Version: 0.1.0
Summary: Python wrapper for Slack Block Kit JSON construction
Author: Abhishek Singh
Author-email: abhisheksinghaz@outlook.com
Classifier: Programming Language :: Python :: 3
Classifier: License :: OSI Approved :: MIT License
Requires-Python: >=3.6
Dynamic: author
Dynamic: author-email
Dynamic: classifier
Dynamic: requires-python
Dynamic: summary
